clipable/__init__.py
clipable/cli.py
clipable-0.1.7.dist-info/entry_points.txt
clipable-0.1.7.dist-info/LICENSE
clipable-0.1.7.dist-info/WHEEL
clipable-0.1.7.dist-info/METADATA
clipable-0.1.7.dist-info/RECORD
