Metadata-Version: 2.1
Name: clipable
Version: 0.1.7
Summary: Your clipboard(Excel or Google spreadsheet) change to markdown clipboard
Home-page: https://github.com/yujikawa/clipable
License: Apache-2.0
Author: yujikawa
Author-email: ykyujikawa@gmail.com
Requires-Python: >=3.7,<4.0
Classifier: License :: OSI Approved :: Apache Software License
Classifier: Programming Language :: Python :: 3
Classifier: Programming Language :: Python :: 3.7
Requires-Dist: pandas (>=1.0,<2.0)
Requires-Dist: pyperclip (>=1.7,<2.0)
Requires-Dist: pytablewriter (>=0.54.0,<0.55.0)
Requires-Dist: tabulate (>=0.8.6,<0.9.0)
Project-URL: Repository, https://github.com/yujikawa/clipable
